bayes_toolbox/__init__.py
bayes_toolbox/glm.py
bayes_toolbox/meta.py
bayes_toolbox-0.1.6.dist-info/licenses/LICENSE
bayes_toolbox-0.1.6.dist-info/METADATA
bayes_toolbox-0.1.6.dist-info/WHEEL
bayes_toolbox-0.1.6.dist-info/top_level.txt
bayes_toolbox-0.1.6.dist-info/RECORD
