Metadata-Version: 2.4
Name: bayes-toolbox
Version: 0.1.6
Summary: A package for performing Bayesian analyses.
Author-email: Hyosub Kim <hyosubkim1@gmail.com>
Project-URL: Homepage, https://github.com/hyosubkim/bayes-toolbox
Project-URL: Bug Tracker, https://github.com/hyosubkim/bayes-toolbox/issues
Project-URL: Documentation, https://hyosubkim.github.io/bayes-toolbox/
Keywords: probabilistic-programming,bayesian-inference,bayesian-statistics,statistics
Classifier: Programming Language :: Python :: 3
Classifier: License :: OSI Approved :: MIT License
Classifier: Operating System :: OS Independent
Requires-Python: >=3.13
License-File: LICENSE
Requires-Dist: arviz~=0.21.0
Requires-Dist: numpy~=2.3.0
Requires-Dist: pandas~=2.2.3
Requires-Dist: pymc~=5.23.0
Requires-Dist: pytensor~=2.31.3
Requires-Dist: setuptools~=78.1.1
Dynamic: license-file
